tarkov_character_and_leaderboard_tool/character_operations.py
tarkov_character_and_leaderboard_tool/config_file.py
tarkov_character_and_leaderboard_tool/leaderboard_functions.py
tarkov_character_and_leaderboard_tool/main.py
tarkov_character_and_leaderboard_tool/utility_funcs.py
tarkov_character_and_leaderboard_tool/venv/Lib/site-packages/_virtualenv.py
tarkov_character_and_leaderboard_tool/venv/Lib/site-packages/_distutils_hack/__init__.py
tarkov_character_and_leaderboard_tool/venv/Lib/site-packages/_distutils_hack/override.py
tarkov_character_and_leaderboard_tool/venv/Lib/site-packages/pip/__init__.py
tarkov_character_and_leaderboard_tool/venv/Lib/site-packages/pip/__main__.py
tarkov_character_and_leaderboard_tool/venv/Lib/site-packages/pip/__pip-runner__.py
tarkov_character_and_leaderboard_tool/venv/Lib/site-packages/pip/_internal/__init__.py
tarkov_character_and_leaderboard_tool/venv/Lib/site-packages/pip/_internal/build_env.py
tarkov_character_and_leaderboard_tool/venv/Lib/site-packages/pip/_internal/cache.py
tarkov_character_and_leaderboard_tool/venv/Lib/site-packages/pip/_internal/configuration.py
tarkov_character_and_leaderboard_tool/venv/Lib/site-packages/pip/_internal/exceptions.py
tarkov_character_and_leaderboard_tool/venv/Lib/site-packages/pip/_internal/main.py
tarkov_character_and_leaderboard_tool/venv/Lib/site-packages/pip/_internal/pyproject.py
tarkov_character_and_leaderboard_tool/venv/Lib/site-packages/pip/_internal/self_outdated_check.py
tarkov_character_and_leaderboard_tool/venv/Lib/site-packages/pip/_internal/wheel_builder.py
tarkov_character_and_leaderboard_tool/venv/Lib/site-packages/pip/_internal/cli/__init__.py
tarkov_character_and_leaderboard_tool/venv/Lib/site-packages/pip/_internal/cli/autocompletion.py
tarkov_character_and_leaderboard_tool/venv/Lib/site-packages/pip/_internal/cli/base_command.py
tarkov_character_and_leaderboard_tool/venv/Lib/site-packages/pip/_internal/cli/cmdoptions.py
TarkovCharacterAndLeaderboardTool-0.1.1.dist-info/LICENSE
TarkovCharacterAndLeaderboardTool-0.1.1.dist-info/METADATA
TarkovCharacterAndLeaderboardTool-0.1.1.dist-info/WHEEL
TarkovCharacterAndLeaderboardTool-0.1.1.dist-info/top_level.txt
TarkovCharacterAndLeaderboardTool-0.1.1.dist-info/RECORD
