Metadata-Version: 2.1
Name: TarkovCharacterAndLeaderboardTool
Version: 0.1.1
Summary: A tool used to create characters for Escape from Tarkov and allows users to rank their characters via leaderboards.
Project-URL: Homepage, https://github.com/kakumei-consulting-mentees/Semester-Project
Classifier: Development Status :: 5 - Production/Stable
Classifier: Intended Audience :: Developers
Classifier: License :: OSI Approved :: MIT License
Classifier: Programming Language :: Python :: 3.11
Requires-Python: >=3.11.1
License-File: LICENSE
Requires-Dist: tabulate
